[
    {
        "id": "CON",
        "elo": 1330.7682674147977
    },
    {
        "id": "LVA",
        "elo": 1497.5870573719544
    },
    {
        "id": "CHI",
        "elo": 1363.3438826578688
    },
    {
        "id": "SEA",
        "elo": 1575.7363174898858
    },
    {
        "id": "DAL",
        "elo": 1396.6607988123963
    },
    {
        "id": "NYL",
        "elo": 1625.6276846899912
    },
    {
        "id": "WAS",
        "elo": 1465.7404577158222
    },
    {
        "id": "PHO",
        "elo": 1539.1971410459319
    },
    {
        "id": "IND",
        "elo": 1539.5689598554582
    },
    {
        "id": "ATL",
        "elo": 1552.7446102947913
    },
    {
        "id": "LAS",
        "elo": 1368.623372678494
    },
    {
        "id": "MIN",
        "elo": 1626.2049918171565
    },
    {
        "id": "GSV",
        "elo": 1418.1955649422457
    }
]