[
    {
        "id": "CON",
        "elo": 1341.239677873395
    },
    {
        "id": "LVA",
        "elo": 1649.2175436418931
    },
    {
        "id": "CHI",
        "elo": 1277.958773561579
    },
    {
        "id": "SEA",
        "elo": 1509.4206103440335
    },
    {
        "id": "DAL",
        "elo": 1337.3035798863705
    },
    {
        "id": "NYL",
        "elo": 1500.152228261464
    },
    {
        "id": "WAS",
        "elo": 1322.190956492224
    },
    {
        "id": "PHO",
        "elo": 1584.3007339334215
    },
    {
        "id": "IND",
        "elo": 1582.9650991685671
    },
    {
        "id": "ATL",
        "elo": 1641.5441185976142
    },
    {
        "id": "LAS",
        "elo": 1433.6011228794537
    },
    {
        "id": "MIN",
        "elo": 1636.5491522604698
    },
    {
        "id": "GSV",
        "elo": 1483.5555098863088
    }
]