[
    {
        "id": "CON",
        "elo": 1593.901199874453
    },
    {
        "id": "LVA",
        "elo": 1671.4909103941045
    },
    {
        "id": "CHI",
        "elo": 1494.4892956641286
    },
    {
        "id": "SEA",
        "elo": 1415.2777630056228
    },
    {
        "id": "DAL",
        "elo": 1526.1457476865003
    },
    {
        "id": "NYL",
        "elo": 1773.6831065109388
    },
    {
        "id": "WAS",
        "elo": 1487.9729448172293
    },
    {
        "id": "PHO",
        "elo": 1313.5276375713431
    },
    {
        "id": "IND",
        "elo": 1365.0464173742275
    },
    {
        "id": "ATL",
        "elo": 1462.2848937645108
    },
    {
        "id": "LAS",
        "elo": 1447.9851589295406
    },
    {
        "id": "MIN",
        "elo": 1448.1913515545757
    }
]