[
    {
        "id": "CON",
        "elo": 1620.0049326372412
    },
    {
        "id": "LVA",
        "elo": 1592.2392736700651
    },
    {
        "id": "CHI",
        "elo": 1513.14567796176
    },
    {
        "id": "SEA",
        "elo": 1551.3938015871165
    },
    {
        "id": "DAL",
        "elo": 1487.8002469986955
    },
    {
        "id": "NYL",
        "elo": 1642.9230995562953
    },
    {
        "id": "WAS",
        "elo": 1385.7786193670863
    },
    {
        "id": "PHO",
        "elo": 1412.1524211131693
    },
    {
        "id": "IND",
        "elo": 1369.5367434229577
    },
    {
        "id": "ATL",
        "elo": 1450.2170769282145
    },
    {
        "id": "LAS",
        "elo": 1411.0334748268865
    },
    {
        "id": "MIN",
        "elo": 1563.7728455040997
    }
]