[
    {
        "id": "CON",
        "elo": 1600.6434660130337
    },
    {
        "id": "LVA",
        "elo": 1707.2401772200483
    },
    {
        "id": "CHI",
        "elo": 1513.1985139227368
    },
    {
        "id": "SEA",
        "elo": 1402.2450365513878
    },
    {
        "id": "DAL",
        "elo": 1560.8610560320735
    },
    {
        "id": "NYL",
        "elo": 1736.0278570921118
    },
    {
        "id": "WAS",
        "elo": 1484.598136249512
    },
    {
        "id": "PHO",
        "elo": 1304.7169537279237
    },
    {
        "id": "IND",
        "elo": 1380.3633713655336
    },
    {
        "id": "ATL",
        "elo": 1435.0002215602979
    },
    {
        "id": "LAS",
        "elo": 1451.2400836004765
    },
    {
        "id": "MIN",
        "elo": 1423.8615538120393
    }
]