[
    {
        "id": "CON",
        "elo": 1475.6493097070538
    },
    {
        "id": "LVA",
        "elo": 1575.8599562248353
    },
    {
        "id": "CHI",
        "elo": 1371.1992440235608
    },
    {
        "id": "SEA",
        "elo": 1548.4616108727114
    },
    {
        "id": "DAL",
        "elo": 1387.8155470158483
    },
    {
        "id": "NYL",
        "elo": 1634.5867048489106
    },
    {
        "id": "WAS",
        "elo": 1484.2644867363695
    },
    {
        "id": "PHO",
        "elo": 1478.815269539964
    },
    {
        "id": "IND",
        "elo": 1516.3188765895877
    },
    {
        "id": "ATL",
        "elo": 1499.1084556325604
    },
    {
        "id": "LAS",
        "elo": 1416.7453139202894
    },
    {
        "id": "MIN",
        "elo": 1595.9977040023005
    },
    {
        "id": "GSV",
        "elo": 1315.1766276728022
    }
]