[
    {
        "id": "CON",
        "elo": 1572.7655130796543
    },
    {
        "id": "LVA",
        "elo": 1586.8235375722907
    },
    {
        "id": "CHI",
        "elo": 1544.4529847866868
    },
    {
        "id": "SEA",
        "elo": 1440.4298629671937
    },
    {
        "id": "DAL",
        "elo": 1511.2921974280189
    },
    {
        "id": "NYL",
        "elo": 1621.7414602266765
    },
    {
        "id": "WAS",
        "elo": 1451.2641108176842
    },
    {
        "id": "PHO",
        "elo": 1443.5253556992022
    },
    {
        "id": "IND",
        "elo": 1392.9019876494176
    },
    {
        "id": "ATL",
        "elo": 1489.9893826569735
    },
    {
        "id": "LAS",
        "elo": 1453.829154467659
    },
    {
        "id": "MIN",
        "elo": 1490.98266622213
    }
]