[
    {
        "id": "CON",
        "elo": 1399.8087953373106
    },
    {
        "id": "LVA",
        "elo": 1599.5877657639692
    },
    {
        "id": "CHI",
        "elo": 1263.6940646209289
    },
    {
        "id": "SEA",
        "elo": 1541.2704627332992
    },
    {
        "id": "DAL",
        "elo": 1300.684675064165
    },
    {
        "id": "NYL",
        "elo": 1548.702311942414
    },
    {
        "id": "WAS",
        "elo": 1376.1904939144752
    },
    {
        "id": "PHO",
        "elo": 1560.4136866928566
    },
    {
        "id": "IND",
        "elo": 1530.5390218822254
    },
    {
        "id": "ATL",
        "elo": 1638.9568394690225
    },
    {
        "id": "LAS",
        "elo": 1422.4144721179077
    },
    {
        "id": "MIN",
        "elo": 1653.2994367819308
    },
    {
        "id": "GSV",
        "elo": 1464.4370804662888
    }
]